plugincode/__init__.py
plugincode/location_provider.py
plugincode/output.py
plugincode/output_filter.py
plugincode/post_scan.py
plugincode/pre_scan.py
plugincode/scan.py
plugincode-31.0.0.dist-info/AUTHORS.rst
plugincode-31.0.0.dist-info/CHANGELOG.rst
plugincode-31.0.0.dist-info/CODE_OF_CONDUCT.rst
plugincode-31.0.0.dist-info/METADATA
plugincode-31.0.0.dist-info/NOTICE
plugincode-31.0.0.dist-info/WHEEL
plugincode-31.0.0.dist-info/apache-2.0.LICENSE
plugincode-31.0.0.dist-info/top_level.txt
plugincode-31.0.0.dist-info/RECORD
